{
  "id": "tools/Impacket/GetUserSPNs.py",
  "title": "GetUserSPNs.py",
  "description": "[[../../../env/active-directory/attacks/Kerberoasting]] across trusts (INLANEFREIGHT is current domain)",
  "source": "@site/notes/tools/Impacket/GetUserSPNs.py.md",
  "sourceDirName": "tools/Impacket",
  "slug": "/tools/Impacket/GetUserSPNs.py",
  "permalink": "/tools/Impacket/GetUserSPNs.py",
  "draft": false,
  "unlisted": false,
  "editUrl": "https://github.com/pwnvault/notes/../notes/tools/Impacket/GetUserSPNs.py.md",
  "tags": [],
  "version": "current",
  "frontMatter": {},
  "sidebar": "PwnGuideSidebar",
  "previous": {
    "title": "Impacket",
    "permalink": "/tools/Impacket/"
  },
  "next": {
    "title": "lookupsid.py",
    "permalink": "/tools/Impacket/lookupsid.py"
  }
}